.travis.yml
MANIFEST.in
README.md
VERSION
build_require.txt
setup.cfg
setup.py
test_require.txt
docs/source/conf.py
docs/source/index.rst
docs/source/_examples/async.py
docs/source/_examples/main.py
pro_lambda/__init__.py
pro_lambda/consts.py
pro_lambda/tools.py
pro_lambda.egg-info/PKG-INFO
pro_lambda.egg-info/SOURCES.txt
pro_lambda.egg-info/dependency_links.txt
pro_lambda.egg-info/top_level.txt
tests/__init__.py
tests/test_main.py