Metadata-Version: 2.1
Name: pro-lambda
Version: 0.1.11
Summary: Lambda with math operators support
Home-page: https://github.com/andvikt/pro_lambda
Author: Viktorov A.G.
Author-email: andvikt@gmail.com
License: MIT
Platform: UNKNOWN
Requires-Python: >=3.7
